{
  "hash": "6004793a14591a972e0da9bd5a69bc48",
  "result": {
    "engine": "knitr",
    "markdown": "# Quais são os 10 processos de classe HC mais antigos no acervo? {#sec-top10}\n\nO objetivo dessa análise é observar os processo da classe HC mais antigos do acervo. As variáveis trabalhadas são \"Classe\"(variável qualitativa) e \"Data de atuação\"(variável qualitativa). Além disso, será evidenciado o código do processo, o relator responsável e o ramo de direito de tal.\n\n\n\n::: {#tbl-top10 .cell tbl-cap='Tabela dos processos de classe HC mais antigos'}\n::: {.cell-output-display}\n\n```{=html}\n<div class=\"datatables html-widget html-fill-item\" id=\"htmlwidget-4b7f0a55552bbd5d633c\" style=\"width:100%;height:auto;\"></div>\n<script type=\"application/json\" data-for=\"htmlwidget-4b7f0a55552bbd5d633c\">{\"x\":{\"filter\":\"none\",\"vertical\":false,\"data\":[[\"94189\",\"111812\",\"154118\",\"164493\",\"166549\",\"167174\",\"172136\",\"174061\",\"176174\",\"181742\"],[\"Min. Marco Aurélio\",\"Min. André Mendonça\",\"Min. Gilmar Mendes\",\"Min. Gilmar Mendes\",\"Min. Gilmar Mendes\",\"Min. Nunes Marques\",\"Min. Nunes Marques\",\"Min. Gilmar Mendes\",\"Min. Nunes Marques\",\"Min. Gilmar Mendes\"],[\"27 de Março de 2008\",\"26 de Dezembro de 2011\",\"12 de Março de 2018\",\"05 de Novembro de 2018\",\"16 de Dezembro de 2018\",\"10 de Janeiro de 2019\",\"04 de Junho de 2019\",\"06 de Agosto de 2019\",\"25 de Setembro de 2019\",\"20 de Fevereiro de 2020\"],[\"Direito Processual Penal\",\"Direito Penal\",\"Direito Processual Penal\",\"Direito Processual Penal\",\"Direito Penal\",\"Direito Eleitoral\",\"Direito Administrativo E Outras Matérias De Direito Público\",\"Direito Processual Penal\",\"Direito Processual Penal\",\"Direito Processual Penal\"]],\"container\":\"<table class=\\\"display\\\">\\n  <thead>\\n    <tr>\\n      <th>Processo<\\/th>\\n      <th>Relator<\\/th>\\n      <th>Data autuação<\\/th>\\n      <th>Ramo do Direito<\\/th>\\n    <\\/tr>\\n  <\\/thead>\\n<\\/table>\",\"options\":{\"pageLength\":10,\"columnDefs\":[{\"name\":\"Processo\",\"targets\":0},{\"name\":\"Relator\",\"targets\":1},{\"name\":\"Data autuação\",\"targets\":2},{\"name\":\"Ramo do Direito\",\"targets\":3}],\"order\":[],\"autoWidth\":false,\"orderClasses\":false}},\"evals\":[],\"jsHooks\":[]}</script>\n```\n\n:::\n:::\n\n\n\nAtravés da @tbl-top10, nota-se muitos processos do direito penal e processual penal. O mesmo dado é confirmado pela @fig-descritiva-top10-2. Além disso, observa-se processos de anos distintos, com o mais velho deles sendo de 2008, isto é, 17 anos atrás. Enquanto isso, o mais recente é de 2019, 6 anos atrás.\n\n\n\n::: {#fig-descritiva-top10 .cell layout-ncol=\"2\"}\n::: {#fig-descritiva-top10-1 .cell-output-display}\n\n```{=html}\n<div class=\"plotly html-widget html-fill-item\" id=\"htmlwidget-f09673c5ce0b44cd71a8\" style=\"width:100%;height:464px;\"></div>\n<script type=\"application/json\" data-for=\"htmlwidget-f09673c5ce0b44cd71a8\">{\"x\":{\"data\":[{\"orientation\":\"h\",\"width\":[0.90000000000000036,0.90000000000000036,0.89999999999999991,0.90000000000000013],\"base\":[0,0,0,0],\"x\":[5,3,1,1],\"y\":[4,3,1,2],\"text\":[\"Relator: Min. Gilmar Mendes <br>Quantidade: 5\",\"Relator: Min. Nunes Marques <br>Quantidade: 3\",\"Relator: Min. André Mendonça <br>Quantidade: 1\",\"Relator: Min. Marco Aurélio <br>Quantidade: 1\"],\"type\":\"bar\",\"textposition\":\"none\",\"marker\":{\"autocolorscale\":false,\"color\":\"rgba(58,68,93,1)\",\"line\":{\"width\":1.8897637795275593,\"color\":\"transparent\"}},\"showlegend\":false,\"xaxis\":\"x\",\"yaxis\":\"y\",\"hoverinfo\":\"text\",\"frame\":null}],\"layout\":{\"margin\":{\"t\":26.228310502283108,\"r\":7.3059360730593621,\"b\":40.182648401826498,\"l\":137.1523453715235},\"plot_bgcolor\":\"rgba(255,255,255,1)\",\"paper_bgcolor\":\"rgba(255,255,255,1)\",\"font\":{\"color\":\"rgba(0,0,0,1)\",\"family\":\"\",\"size\":14.611872146118724},\"xaxis\":{\"domain\":[0,1],\"automargin\":true,\"type\":\"linear\",\"autorange\":false,\"range\":[-0.25,5.25],\"tickmode\":\"array\",\"ticktext\":[\"0\",\"1\",\"2\",\"3\",\"4\",\"5\"],\"tickvals\":[0,1,2,3,4,5],\"categoryorder\":\"array\",\"categoryarray\":[\"0\",\"1\",\"2\",\"3\",\"4\",\"5\"],\"nticks\":null,\"ticks\":\"outside\",\"tickcolor\":\"rgba(51,51,51,1)\",\"ticklen\":3.6529680365296811,\"tickwidth\":0.66417600664176002,\"showticklabels\":true,\"tickfont\":{\"color\":\"rgba(77,77,77,1)\",\"family\":\"\",\"size\":11.68949771689498},\"tickangle\":-0,\"showline\":false,\"linecolor\":null,\"linewidth\":0,\"showgrid\":true,\"gridcolor\":\"rgba(235,235,235,1)\",\"gridwidth\":0.66417600664176002,\"zeroline\":false,\"anchor\":\"y\",\"title\":{\"text\":\"Quantidade\",\"font\":{\"color\":\"rgba(0,0,0,1)\",\"family\":\"\",\"size\":14.611872146118724}},\"hoverformat\":\".2f\"},\"yaxis\":{\"domain\":[0,1],\"automargin\":true,\"type\":\"linear\",\"autorange\":false,\"range\":[0.40000000000000002,4.5999999999999996],\"tickmode\":\"array\",\"ticktext\":[\"Min. André Mendonça\",\"Min. Marco Aurélio\",\"Min. Nunes Marques\",\"Min. Gilmar Mendes\"],\"tickvals\":[1,2,3,4],\"categoryorder\":\"array\",\"categoryarray\":[\"Min. André Mendonça\",\"Min. Marco Aurélio\",\"Min. Nunes Marques\",\"Min. Gilmar Mendes\"],\"nticks\":null,\"ticks\":\"outside\",\"tickcolor\":\"rgba(51,51,51,1)\",\"ticklen\":3.6529680365296811,\"tickwidth\":0.66417600664176002,\"showticklabels\":true,\"tickfont\":{\"color\":\"rgba(77,77,77,1)\",\"family\":\"\",\"size\":13.283520132835205},\"tickangle\":-0,\"showline\":false,\"linecolor\":null,\"linewidth\":0,\"showgrid\":true,\"gridcolor\":\"rgba(235,235,235,1)\",\"gridwidth\":0.66417600664176002,\"zeroline\":false,\"anchor\":\"x\",\"title\":{\"text\":\"\",\"font\":{\"color\":\"rgba(0,0,0,1)\",\"family\":\"\",\"size\":14.611872146118724}},\"hoverformat\":\".2f\"},\"shapes\":[{\"type\":\"rect\",\"fillcolor\":\"transparent\",\"line\":{\"color\":\"rgba(51,51,51,1)\",\"width\":0.66417600664176002,\"linetype\":\"solid\"},\"yref\":\"paper\",\"xref\":\"paper\",\"x0\":0,\"x1\":1,\"y0\":0,\"y1\":1}],\"showlegend\":false,\"legend\":{\"bgcolor\":\"rgba(255,255,255,1)\",\"bordercolor\":\"transparent\",\"borderwidth\":1.8897637795275593,\"font\":{\"color\":\"rgba(0,0,0,1)\",\"family\":\"\",\"size\":11.68949771689498}},\"hovermode\":\"closest\",\"barmode\":\"relative\"},\"config\":{\"doubleClick\":\"reset\",\"modeBarButtonsToAdd\":[\"hoverclosest\",\"hovercompare\"],\"showSendToCloud\":false},\"source\":\"A\",\"attrs\":{\"7b3273994f78\":{\"x\":{},\"y\":{},\"text\":{},\"type\":\"bar\"}},\"cur_data\":\"7b3273994f78\",\"visdat\":{\"7b3273994f78\":[\"function (y) \",\"x\"]},\"highlight\":{\"on\":\"plotly_click\",\"persistent\":false,\"dynamic\":false,\"selectize\":false,\"opacityDim\":0.20000000000000001,\"selected\":{\"opacity\":1},\"debounce\":0},\"shinyEvents\":[\"plotly_hover\",\"plotly_click\",\"plotly_selected\",\"plotly_relayout\",\"plotly_brushed\",\"plotly_brushing\",\"plotly_clickannotation\",\"plotly_doubleclick\",\"plotly_deselect\",\"plotly_afterplot\",\"plotly_sunburstclick\"],\"base_url\":\"https://plot.ly\"},\"evals\":[],\"jsHooks\":[]}</script>\n```\n\n\nMinistros\n:::\n\n::: {#fig-descritiva-top10-2 .cell-output-display}\n\n```{=html}\n<div class=\"plotly html-widget html-fill-item\" id=\"htmlwidget-7677e1c744a34bf93c88\" style=\"width:100%;height:464px;\"></div>\n<script type=\"application/json\" data-for=\"htmlwidget-7677e1c744a34bf93c88\">{\"x\":{\"data\":[{\"orientation\":\"h\",\"width\":[0.90000000000000036,0.90000000000000036,0.89999999999999991,0.90000000000000013],\"base\":[0,0,0,0],\"x\":[6,2,1,1],\"y\":[4,3,1,2],\"text\":[\"Ramo: Direito Processual Penal <br>Quantidade: 6\",\"Ramo: Direito Penal <br>Quantidade: 2\",\"Ramo: Direito Administrativo E Outras Matérias De Direito Público <br>Quantidade: 1\",\"Ramo: Direito Eleitoral <br>Quantidade: 1\"],\"type\":\"bar\",\"textposition\":\"none\",\"marker\":{\"autocolorscale\":false,\"color\":\"rgba(58,68,93,1)\",\"line\":{\"width\":1.8897637795275593,\"color\":\"transparent\"}},\"showlegend\":false,\"xaxis\":\"x\",\"yaxis\":\"y\",\"hoverinfo\":\"text\",\"frame\":null}],\"layout\":{\"margin\":{\"t\":26.228310502283108,\"r\":7.3059360730593621,\"b\":40.182648401826498,\"l\":183.64466583644671},\"plot_bgcolor\":\"rgba(255,255,255,1)\",\"paper_bgcolor\":\"rgba(255,255,255,1)\",\"font\":{\"color\":\"rgba(0,0,0,1)\",\"family\":\"\",\"size\":14.611872146118724},\"xaxis\":{\"domain\":[0,1],\"automargin\":true,\"type\":\"linear\",\"autorange\":false,\"range\":[-0.30000000000000004,6.2999999999999998],\"tickmode\":\"array\",\"ticktext\":[\"0\",\"2\",\"4\",\"6\"],\"tickvals\":[0,1.9999999999999998,4,6],\"categoryorder\":\"array\",\"categoryarray\":[\"0\",\"2\",\"4\",\"6\"],\"nticks\":null,\"ticks\":\"outside\",\"tickcolor\":\"rgba(51,51,51,1)\",\"ticklen\":3.6529680365296811,\"tickwidth\":0.66417600664176002,\"showticklabels\":true,\"tickfont\":{\"color\":\"rgba(77,77,77,1)\",\"family\":\"\",\"size\":11.68949771689498},\"tickangle\":-0,\"showline\":false,\"linecolor\":null,\"linewidth\":0,\"showgrid\":true,\"gridcolor\":\"rgba(235,235,235,1)\",\"gridwidth\":0.66417600664176002,\"zeroline\":false,\"anchor\":\"y\",\"title\":{\"text\":\"Quantidade\",\"font\":{\"color\":\"rgba(0,0,0,1)\",\"family\":\"\",\"size\":14.611872146118724}},\"hoverformat\":\".2f\"},\"yaxis\":{\"domain\":[0,1],\"automargin\":true,\"type\":\"linear\",\"autorange\":false,\"range\":[0.40000000000000002,4.5999999999999996],\"tickmode\":\"array\",\"ticktext\":[\"Direito Administrativo E<br />Outras Matérias De Direito<br />Público\",\"Direito Eleitoral\",\"Direito Penal\",\"Direito Processual Penal\"],\"tickvals\":[1,2,3,4],\"categoryorder\":\"array\",\"categoryarray\":[\"Direito Administrativo E<br />Outras Matérias De Direito<br />Público\",\"Direito Eleitoral\",\"Direito Penal\",\"Direito Processual Penal\"],\"nticks\":null,\"ticks\":\"outside\",\"tickcolor\":\"rgba(51,51,51,1)\",\"ticklen\":3.6529680365296811,\"tickwidth\":0.66417600664176002,\"showticklabels\":true,\"tickfont\":{\"color\":\"rgba(77,77,77,1)\",\"family\":\"\",\"size\":13.283520132835205},\"tickangle\":-0,\"showline\":false,\"linecolor\":null,\"linewidth\":0,\"showgrid\":true,\"gridcolor\":\"rgba(235,235,235,1)\",\"gridwidth\":0.66417600664176002,\"zeroline\":false,\"anchor\":\"x\",\"title\":{\"text\":\"\",\"font\":{\"color\":\"rgba(0,0,0,1)\",\"family\":\"\",\"size\":14.611872146118724}},\"hoverformat\":\".2f\"},\"shapes\":[{\"type\":\"rect\",\"fillcolor\":\"transparent\",\"line\":{\"color\":\"rgba(51,51,51,1)\",\"width\":0.66417600664176002,\"linetype\":\"solid\"},\"yref\":\"paper\",\"xref\":\"paper\",\"x0\":0,\"x1\":1,\"y0\":0,\"y1\":1}],\"showlegend\":false,\"legend\":{\"bgcolor\":\"rgba(255,255,255,1)\",\"bordercolor\":\"transparent\",\"borderwidth\":1.8897637795275593,\"font\":{\"color\":\"rgba(0,0,0,1)\",\"family\":\"\",\"size\":11.68949771689498}},\"hovermode\":\"closest\",\"barmode\":\"relative\"},\"config\":{\"doubleClick\":\"reset\",\"modeBarButtonsToAdd\":[\"hoverclosest\",\"hovercompare\"],\"showSendToCloud\":false},\"source\":\"A\",\"attrs\":{\"7b322479d99c\":{\"x\":{},\"y\":{},\"text\":{},\"type\":\"bar\"}},\"cur_data\":\"7b322479d99c\",\"visdat\":{\"7b322479d99c\":[\"function (y) \",\"x\"]},\"highlight\":{\"on\":\"plotly_click\",\"persistent\":false,\"dynamic\":false,\"selectize\":false,\"opacityDim\":0.20000000000000001,\"selected\":{\"opacity\":1},\"debounce\":0},\"shinyEvents\":[\"plotly_hover\",\"plotly_click\",\"plotly_selected\",\"plotly_relayout\",\"plotly_brushed\",\"plotly_brushing\",\"plotly_clickannotation\",\"plotly_doubleclick\",\"plotly_deselect\",\"plotly_afterplot\",\"plotly_sunburstclick\"],\"base_url\":\"https://plot.ly\"},\"evals\":[],\"jsHooks\":[]}</script>\n```\n\n\nRamo de direito\n:::\n\nGráficos de coluna referente aos relatores e o ramo dos processos mais antigos\n:::\n\n\n\nAcerca dos relatores responsáveis por estes processos, o Ministro Gilmar Mendes é responsável por 5 destes processos. Ele é o relator que mais aparece seguido do Ministro Nunes Marques com 3 processos.\n\nEnquanto isso, os Ministros Marco Aurélio e André Mendonça possuem 1 processo cada. Nota-se também que eles são os responsáveis pelos dois processos mais antigos com os códigos 94189(2008) e 111812(2011), respectivamente.\n",
    "supporting": [],
    "filters": [
      "rmarkdown/pagebreak.lua"
    ],
    "includes": {
      "include-in-header": [
        "<link href=\"../site_libs/htmltools-fill-0.5.8.1/fill.css\" rel=\"stylesheet\" />\n<script src=\"../site_libs/htmlwidgets-1.6.4/htmlwidgets.js\"></script>\n<link href=\"../site_libs/datatables-css-0.0.0/datatables-crosstalk.css\" rel=\"stylesheet\" />\n<script src=\"../site_libs/datatables-binding-0.33/datatables.js\"></script>\n<script src=\"../site_libs/jquery-3.6.0/jquery-3.6.0.min.js\"></script>\n<link href=\"../site_libs/dt-core-1.13.6/css/jquery.dataTables.min.css\" rel=\"stylesheet\" />\n<link href=\"../site_libs/dt-core-1.13.6/css/jquery.dataTables.extra.css\" rel=\"stylesheet\" />\n<script src=\"../site_libs/dt-core-1.13.6/js/jquery.dataTables.min.js\"></script>\n<link href=\"../site_libs/crosstalk-1.2.1/css/crosstalk.min.css\" rel=\"stylesheet\" />\n<script src=\"../site_libs/crosstalk-1.2.1/js/crosstalk.min.js\"></script>\n<script src=\"../site_libs/plotly-binding-4.10.4/plotly.js\"></script>\n<script src=\"../site_libs/typedarray-0.1/typedarray.min.js\"></script>\n<link href=\"../site_libs/plotly-htmlwidgets-css-2.11.1/plotly-htmlwidgets.css\" rel=\"stylesheet\" />\n<script src=\"../site_libs/plotly-main-2.11.1/plotly-latest.min.js\"></script>\n"
      ]
    },
    "engineDependencies": {},
    "preserve": {},
    "postProcess": true
  }
}